genome_grist/Snakefile
genome_grist/__init__.py
genome_grist/__main__.py
genome_grist/combine_csvs.py
genome_grist/copy_local_genomes.py
genome_grist/make_info_file.py
genome_grist/remove_idents_from_manifest.py
genome_grist/subtract_gather.py
genome_grist/summarize_gather_hashes.py
genome_grist/summarize_mapping.py
genome_grist/version.py
genome_grist/conf/defaults.conf
genome_grist/conf/system.conf
genome_grist/env/abundtrim.yml
genome_grist/env/bcftools.yml
genome_grist/env/covtobed.yml
genome_grist/env/minimap2.yml
genome_grist/env/papermill.yml
genome_grist/env/sourmash.yml
genome_grist/env/sra.yml
genome_grist/env/trim.yml
genome_grist/env/wget.yml
genome_grist/notebooks/report-gather.ipynb
genome_grist/notebooks/report-mapping.ipynb
genome_grist/notebooks/report-taxonomy.ipynb
genome_grist-0.11.7.dist-info/licenses/LICENSE.txt
genome_grist-0.11.7.dist-info/METADATA
genome_grist-0.11.7.dist-info/WHEEL
genome_grist-0.11.7.dist-info/entry_points.txt
genome_grist-0.11.7.dist-info/top_level.txt
genome_grist-0.11.7.dist-info/RECORD
