Metadata-Version: 2.4
Name: genome-grist
Version: 0.11.7
Summary: tools to support genome and metagenome analysis
Author: C. Titus Brown, Luiz Irber, N. Tessa Pierce-Ward, Taylor Reiter
Classifier: Environment :: Console
Classifier: Environment :: MacOS X
Classifier: Intended Audience :: Science/Research
Classifier: License :: OSI Approved :: BSD License
Classifier: Natural Language :: English
Classifier: Operating System :: POSIX :: Linux
Classifier: Operating System :: MacOS :: MacOS X
Classifier: Programming Language :: Python :: 3.12
Classifier: Topic :: Scientific/Engineering :: Bio-Informatics
Requires-Python: >=3.12
License-File: LICENSE.txt
Requires-Dist: snakemake
Requires-Dist: click<9,>=7
Requires-Dist: pandas<3,>1
Requires-Dist: polars<2,>=1.30
Requires-Dist: get-some-ncbi-genomes<0.4,>=0.3.3
Provides-Extra: test
Requires-Dist: sourmash<5,>=4.9.0; extra == "test"
Requires-Dist: pytest<8.5.0,>=6.2.4; extra == "test"
Requires-Dist: pytest-dependency==0.6.0; extra == "test"
Dynamic: license-file
